revenv/__init__.py
revenv/cli.py
revenv/func.py
revenv/logging_config.py
revenv-0.0.5.dist-info/LICENSE
revenv-0.0.5.dist-info/METADATA
revenv-0.0.5.dist-info/WHEEL
revenv-0.0.5.dist-info/entry_points.txt
revenv-0.0.5.dist-info/top_level.txt
revenv-0.0.5.dist-info/RECORD
